tesseract_table_preprocessor/__init__.py
tesseract_table_preprocessor/model.py
tesseract_table_preprocessor/state_dict.pt
tesseract_table_preprocessor-0.0.3.dist-info/LICENSE.txt
tesseract_table_preprocessor-0.0.3.dist-info/METADATA
tesseract_table_preprocessor-0.0.3.dist-info/WHEEL
tesseract_table_preprocessor-0.0.3.dist-info/top_level.txt
tesseract_table_preprocessor-0.0.3.dist-info/RECORD
